{
 "align_labels_right": 0, 
 "creation": "2017-11-22 17:59:35.868690", 
 "css": ".print-heading {\nmargin-top: -40px;\n}", 
 "custom_format": 0, 
 "disabled": 0, 
 "doc_type": "Quotation", 
 "docstatus": 0, 
 "doctype": "Print Format", 
 "font": "Default", 
 "format_data": "[{\"fieldname\": \"print_heading_template\", \"fieldtype\": \"Custom HTML\", \"options\": \"<div class=\\\"print-heading\\\">\\t\\t\\t\\t<h2>Confirmaci\\u00f3n de Pedido</h2></div>\"}, {\"fieldtype\": \"Section Break\", \"label\": \"\"}, {\"fieldtype\": \"Column Break\"}, {\"print_hide\": 0, \"label\": \"Custom HTML\", \"fieldname\": \"_custom_html\", \"options\": \"<div class=\\\"row section-break\\\">\\n\\t\\t\\t<div class=\\\"col-xs-4 column-break\\\">\\n            \\n<div class=\\\"row  data-field row-border\\\">\\n<div class=\\\"col-xs-6 bg-dark\\\">PEDIDO N\\u00ba :</div>\\n<div class=\\\"col-xs-6 text-right\\\">{{doc.name}}</div>\\n</div>\\n<div class=\\\"row  data-field  row-border\\\">\\n<div class=\\\"col-xs-6 bg-dark\\\">FECHA :</div>\\n<div class=\\\"col-xs-6 text-right\\\">{{doc.transaction_date}}</div>\\n</div>\\n            \\n           \\n\\t\\t\\t</div>\\n        \\n\\t\\t\\t<div class=\\\"col-xs-7 col-xs-offset-1 column-break\\\">\\n            \\n                <div><h4 class=\\\"no-margin-top\\\">{{doc.customer}}</h4>\\n{{doc.address_display}}<br></div>\\n            \\n                <div>Att. {{doc.contact_display}}</div>\\n            \\n\\t\\t\\t</div>\\n        \\n    </div>\", \"fieldtype\": \"HTML\"}, {\"fieldtype\": \"Section Break\", \"label\": \"\"}, {\"fieldtype\": \"Column Break\"}, {\"visible_columns\": [{\"print_hide\": 0, \"fieldname\": \"item_code\", \"print_width\": \"150px\"}, {\"print_hide\": 0, \"fieldname\": \"description\", \"print_width\": \"300px\"}, {\"print_hide\": 0, \"fieldname\": \"image\", \"print_width\": \"\"}, {\"print_hide\": 0, \"fieldname\": \"qty\", \"print_width\": \"100px\"}, {\"print_hide\": 0, \"fieldname\": \"stock_uom\", \"print_width\": \"100px\"}, {\"print_hide\": 0, \"fieldname\": \"uom\", \"print_width\": \"\"}, {\"print_hide\": 0, \"fieldname\": \"rate\", \"print_width\": \"100px\"}, {\"print_hide\": 0, \"fieldname\": \"amount\", \"print_width\": \"100px\"}, {\"print_hide\": 0, \"fieldname\": \"pricing_rule\", \"print_width\": \"\"}, {\"print_hide\": 0, \"fieldname\": \"stock_balance\", \"print_width\": \"\"}], \"print_hide\": 0, \"fieldname\": \"items\", \"label\": \"Items\"}, {\"fieldtype\": \"Section Break\", \"label\": \"\"}, {\"fieldtype\": \"Column Break\"}, {\"fieldtype\": \"Column Break\"}, {\"print_hide\": 0, \"fieldname\": \"total\", \"label\": \"Total\"}, {\"fieldtype\": \"Section Break\", \"label\": \"\"}, {\"fieldtype\": \"Column Break\"}, {\"visible_columns\": [{\"print_hide\": 0, \"fieldname\": \"charge_type\", \"print_width\": \"\"}, {\"print_hide\": 0, \"fieldname\": \"row_id\", \"print_width\": \"\"}, {\"print_hide\": 0, \"fieldname\": \"account_head\", \"print_width\": \"\"}, {\"print_hide\": 0, \"fieldname\": \"cost_center\", \"print_width\": \"\"}, {\"print_hide\": 0, \"fieldname\": \"description\", \"print_width\": \"300px\"}, {\"print_hide\": 0, \"fieldname\": \"rate\", \"print_width\": \"\"}, {\"print_hide\": 0, \"fieldname\": \"tax_amount\", \"print_width\": \"\"}, {\"print_hide\": 0, \"fieldname\": \"total\", \"print_width\": \"\"}, {\"print_hide\": 0, \"fieldname\": \"tax_amount_after_discount_amount\", \"print_width\": \"\"}, {\"print_hide\": 0, \"fieldname\": \"base_tax_amount\", \"print_width\": \"\"}, {\"print_hide\": 0, \"fieldname\": \"base_total\", \"print_width\": \"\"}, {\"print_hide\": 0, \"fieldname\": \"base_tax_amount_after_discount_amount\", \"print_width\": \"\"}, {\"print_hide\": 0, \"fieldname\": \"item_wise_tax_detail\", \"print_width\": \"\"}], \"print_hide\": 0, \"fieldname\": \"taxes\", \"label\": \"Sales Taxes and Charges\"}, {\"fieldtype\": \"Section Break\", \"label\": \"\"}, {\"fieldtype\": \"Column Break\"}, {\"fieldtype\": \"Column Break\"}, {\"print_hide\": 0, \"fieldname\": \"grand_total\", \"label\": \"Grand Total\"}, {\"fieldtype\": \"Section Break\", \"label\": \"Terms\"}, {\"fieldtype\": \"Column Break\"}, {\"print_hide\": 0, \"fieldname\": \"terms\", \"label\": \"Term Details\"}, {\"fieldtype\": \"Section Break\", \"label\": \"\"}, {\"fieldtype\": \"Column Break\"}, {\"print_hide\": 0, \"label\": \"Custom HTML\", \"fieldname\": \"_custom_html\", \"options\": \"METALGR\\u00c1FICA DEL SUR, S.L.U.\\n<br>\\n<br>\\n<br>\\n<br>\\n{{ frappe.user }}\", \"fieldtype\": \"HTML\"}]", 
 "idx": 0, 
 "line_breaks": 0, 
 "modified": "2017-11-22 20:39:59.837338", 
 "modified_by": "Administrator", 
 "module": "Selling", 
 "name": "Confirmacion de Pedido", 
 "owner": "Administrator", 
 "print_format_builder": 1, 
 "print_format_type": "Server", 
 "show_section_headings": 0, 
 "standard": "Yes"
}